{
    "headerTitle": "My Website",
    "headerParagraph": "Resize the browser window to see the effect.",
    "navbar-option-1": "Link",
    "navbar-option-2": "Link",
    "navbar-option-3": "Link",
    "navbar-option-4": "Link",
    "card1-h2": "TITLE HEADING",
    "card1-h5": "Title description, Dec 7, 2017",
    "card1-p1": "Some text..",
    "card1-p2": "Sunt in culpa qui officia deserunt mollit anim id est laborum consectetur adipiscing elit, sed do eiusmod tempor incididunt ut labore et dolore magna aliqua. Ut enim ad minim veniam, quis nostrud exercitation ullamco.",
    "card2-h2": "TITLE HEADING",
    "card2-h5": "Title description, Dec 7, 2017",
    "card2-p1": "Some text..",
    "card2-p2": "Sunt in culpa qui officia deserunt mollit anim id est laborum consectetur adipiscing elit, sed do eiusmod tempor incididunt ut labore et dolore magna aliqua. Ut enim ad minim veniam, quis nostrud exercitation ullamco.",
    "card3-h2": "About Me",
    "card3-p": "Some text about me in culpa qui officia deserunt mollit anim.",
    "card4-h3": "Popular Post",
    "card4-img1": "Image",
    "card4-img2": "Image",
    "card4-img3": "Image",
    "card5-h3": "Follow Me",
    "card5-p": "Some text..",
    "footer-h2": "Footer"
}